{
    "1681928752665743:115073": {
        "IResourceController": {
            "name": "Assets",
            "type": 0,
            "subtype": -1,
            "dependency": 0,
            "hidden": false,
            "publicId": "1681928752665935:115074",
            "resources": [
                "1681928757570226:118790",
                "1681928767677932:123201",
                "1681928786757932:131531",
                "1681928799390036:137039",
                "1681928807819934:140723",
                "1681928817988822:145152"
            ]
        }
    },
    "1681928752665935:115074": {
        "IResourceController": {
            "public": {
                "path": "Assets"
            }
        }
    }
}
